{
  "tiles" : [ {
    "scaleFactors" : [ 32, 16, 8, 4, 2, 1 ],
    "width" : 1024,
    "height" : 1024
  } ],
  "protocol" : "http://iiif.io/api/image",
  "sizes" : [ {
    "width" : 195,
    "height" : 279
  }, {
    "width" : 389,
    "height" : 557
  }, {
    "width" : 778,
    "height" : 1114
  }, {
    "width" : 1556,
    "height" : 2228
  }, {
    "width" : 3111,
    "height" : 4455
  }, {
    "width" : 6222,
    "height" : 8909
  } ],
  "profile" : "http://iiif.io/api/image/2/level0.json",
  "width" : 6222,
  "@id" : "https://aldon9.github.io/Seidenindustrie/images/StAZH_PLAN_A_31",
  "@context" : "http://iiif.io/api/image/2/context.json",
  "height" : 8909
}